odoo/addons/website_product_configurator/README.md
odoo/addons/website_product_configurator/__init__.py
odoo/addons/website_product_configurator/__manifest__.py
odoo/addons/website_product_configurator/controllers/__init__.py
odoo/addons/website_product_configurator/controllers/main.py
odoo/addons/website_product_configurator/data/config_form_templates.xml
odoo/addons/website_product_configurator/data/cron.xml
odoo/addons/website_product_configurator/data/ir_config_parameter_data.xml
odoo/addons/website_product_configurator/demo/product_template_demo.xml
odoo/addons/website_product_configurator/i18n/de.po
odoo/addons/website_product_configurator/i18n/website_product_configurator.pot
odoo/addons/website_product_configurator/models/__init__.py
odoo/addons/website_product_configurator/models/product_config.py
odoo/addons/website_product_configurator/models/res_config_settings.py
odoo/addons/website_product_configurator/models/sale_order.py
odoo/addons/website_product_configurator/security/configurator_security.xml
odoo/addons/website_product_configurator/static/description/cover.png
odoo/addons/website_product_configurator/static/description/icon.png
odoo/addons/website_product_configurator/static/src/css/config_form.css
odoo/addons/website_product_configurator/static/src/css/tooltip.css
odoo/addons/website_product_configurator/static/src/js/config_form.js
odoo/addons/website_product_configurator/static/src/js/website_config_tour.js
odoo/addons/website_product_configurator/static/src/js/website_sale.js
odoo/addons/website_product_configurator/static/src/scss/config_form.scss
odoo/addons/website_product_configurator/static/src/scss/tooltip.scss
odoo/addons/website_product_configurator/tests/__init__.py
odoo/addons/website_product_configurator/tests/test_product_config.py
odoo/addons/website_product_configurator/tests/test_res_config_settings.py
odoo/addons/website_product_configurator/tests/test_sale_order.py
odoo14_addon_website_product_configurator-14.0.1.2.0.dist-info/METADATA
odoo14_addon_website_product_configurator-14.0.1.2.0.dist-info/WHEEL
odoo14_addon_website_product_configurator-14.0.1.2.0.dist-info/top_level.txt
odoo14_addon_website_product_configurator-14.0.1.2.0.dist-info/RECORD
